filezen/__init__.py
filezen/version.py
filezen/advancedScanner/__init__.py
filezen/advancedScanner/advancedscanner.py
filezen/frequencyHeap/__init__.py
filezen/frequencyHeap/frequencyheap.py
filezen/scanner/__init__.py
filezen/scanner/scanner.py
filezen/simpleScanner/__init__.py
filezen/simpleScanner/extensionMapper.py
filezen/simpleScanner/simplescanner.py
tests/__init__.py
tests/test_advancedScanner.py
tests/test_frequencyHeap.py
tests/test_scanner.py
tests/test_simpleScanner.py
Filezen-1.5.3.dist-info/LICENSE
Filezen-1.5.3.dist-info/METADATA
Filezen-1.5.3.dist-info/WHEEL
Filezen-1.5.3.dist-info/top_level.txt
Filezen-1.5.3.dist-info/RECORD
