Metadata-Version: 2.1
Name: Filezen
Version: 1.5.3
Summary: An Intelligent file organizer module that reads your file storing pattern
Home-page: https://github.com/ab-anand/Filezen
Author: Abhinav Anand
Author-email: abhinavanand1905@gmail.com
License: MIT
Download-URL: https://github.com/ab-anand/Filezen/tarball/1.5.3
Keywords: Operating System,Utility,Automation,Heaps,File Organizer
Platform: UNKNOWN
Classifier: Intended Audience :: Developers
Classifier: License :: OSI Approved :: MIT License
Classifier: Natural Language :: English
Classifier: Programming Language :: Python
Classifier: Programming Language :: Python :: 2.7
Classifier: Programming Language :: Python :: 3.4
Classifier: Programming Language :: Python :: 3.6
Classifier: Programming Language :: Python :: 3.8
Classifier: Topic :: System
Classifier: Topic :: System :: Operating System
Classifier: Topic :: Utilities
Classifier: Topic :: Software Development
Classifier: Topic :: Software Development :: Libraries
Requires-Dist: pathlib (>=1.0.1)
Requires-Dist: setuptools (>=44.1.1)
